planet_ruler/__init__.py
planet_ruler/annotate.py
planet_ruler/camera.py
planet_ruler/cli.py
planet_ruler/dashboard.py
planet_ruler/demo.py
planet_ruler/fit.py
planet_ruler/geometry.py
planet_ruler/image.py
planet_ruler/observation.py
planet_ruler/plot.py
planet_ruler/uncertainty.py
planet_ruler/validation.py
planet_ruler-1.7.0.dist-info/METADATA
planet_ruler-1.7.0.dist-info/WHEEL
planet_ruler-1.7.0.dist-info/entry_points.txt
planet_ruler-1.7.0.dist-info/licenses/LICENSE
planet_ruler-1.7.0.dist-info/RECORD
