Metadata-Version: 2.4
Name: planet-ruler
Version: 1.7.0
Summary: Measure planetary radii from horizon photographs using computer vision and geometry
Project-URL: Homepage, https://github.com/bogsdarking/planet_ruler
Project-URL: Repository, https://github.com/bogsdarking/planet_ruler
Project-URL: Issues, https://github.com/bogsdarking/planet_ruler/issues
Project-URL: Documentation, https://bogsdarking.github.io/planet_ruler/
Author-email: Brandon Anderson <bogsdarking@proton.me>
License-File: LICENSE
Classifier: Development Status :: 4 - Beta
Classifier: Intended Audience :: Education
Classifier: Intended Audience :: Science/Research
Classifier: License :: OSI Approved :: Apache Software License
Classifier: Operating System :: OS Independent
Classifier: Programming Language :: Python :: 3
Classifier: Programming Language :: Python :: 3.8
Classifier: Programming Language :: Python :: 3.9
Classifier: Programming Language :: Python :: 3.10
Classifier: Programming Language :: Python :: 3.11
Classifier: Programming Language :: Python :: 3.12
Classifier: Topic :: Education
Classifier: Topic :: Scientific/Engineering :: Astronomy
Classifier: Topic :: Scientific/Engineering :: Image Processing
Classifier: Topic :: Scientific/Engineering :: Mathematics
Requires-Python: >=3.8
Requires-Dist: ipython<9.0.0,>=7.16.0
Requires-Dist: ipywidgets<9.0.0,>=7.6.0
Requires-Dist: kagglehub<1.0.0,>=0.1.0; python_version >= '3.9'
Requires-Dist: matplotlib<4.0.0,>=3.5.0
Requires-Dist: numpy<2.0.0,>=1.20.0
Requires-Dist: opencv-python<5.0.0,>=4.5.0
Requires-Dist: pandas<3.0.0,>=1.3.0
Requires-Dist: pillow<12.0.0,>=8.0.0
Requires-Dist: pyyaml<7.0.0,>=5.4.0
Requires-Dist: scipy<2.0.0,>=1.7.0
Requires-Dist: seaborn<1.0.0,>=0.11.0
Requires-Dist: segment-anything<2.0.0,>=1.0; python_version >= '3.8' and platform_system != 'Darwin' or python_version >= '3.9'
Requires-Dist: tqdm<5.0.0,>=4.60.0
Provides-Extra: all
Requires-Dist: ipython<9.0.0,>=7.16.0; extra == 'all'
Requires-Dist: ipywidgets<9.0.0,>=7.6.0; extra == 'all'
Requires-Dist: jupyter-core<6.0.0,>=4.0.0; extra == 'all'
Requires-Dist: jupyter<2.0.0,>=1.0.0; extra == 'all'
Requires-Dist: segment-anything<2.0.0,>=1.0; extra == 'all'
Requires-Dist: torch<3.0.0,>=1.11.0; extra == 'all'
Requires-Dist: torchvision; extra == 'all'
Provides-Extra: dev
Requires-Dist: black>=22.0.0; extra == 'dev'
Requires-Dist: flake8>=6.0.0; extra == 'dev'
Requires-Dist: isort>=5.12.0; extra == 'dev'
Requires-Dist: pytest-cov>=4.0.0; extra == 'dev'
Requires-Dist: pytest>=7.0.0; extra == 'dev'
Provides-Extra: jupyter
Requires-Dist: ipython<9.0.0,>=7.16.0; extra == 'jupyter'
Requires-Dist: ipywidgets<9.0.0,>=7.6.0; extra == 'jupyter'
Requires-Dist: jupyter-core<6.0.0,>=4.0.0; extra == 'jupyter'
Requires-Dist: jupyter<2.0.0,>=1.0.0; extra == 'jupyter'
Provides-Extra: minimal
Requires-Dist: matplotlib<4.0.0,>=3.5.0; extra == 'minimal'
Requires-Dist: numpy<2.0.0,>=1.20.0; extra == 'minimal'
Requires-Dist: opencv-python<5.0.0,>=4.5.0; extra == 'minimal'
Requires-Dist: pandas<3.0.0,>=1.3.0; extra == 'minimal'
Requires-Dist: pillow<12.0.0,>=8.0.0; extra == 'minimal'
Requires-Dist: pyyaml<7.0.0,>=5.4.0; extra == 'minimal'
Requires-Dist: scipy<2.0.0,>=1.7.0; extra == 'minimal'
Requires-Dist: seaborn<1.0.0,>=0.11.0; extra == 'minimal'
Requires-Dist: tqdm<5.0.0,>=4.60.0; extra == 'minimal'
Provides-Extra: ml
Requires-Dist: segment-anything<2.0.0,>=1.0; extra == 'ml'
Requires-Dist: torch<3.0.0,>=1.11.0; extra == 'ml'
Requires-Dist: torchvision; extra == 'ml'
